tests/__init__.py
tests/test_daemon_rpc.py
tests/test_daemon_ws.py
tests/test_wallet_rpc.py
tests/test_wallet_ws.py
tests/test_xswd.py
xelis/__init__.py
xelis/config/__init__.py
xelis/config/module.py
xelis/daemon/__init__.py
xelis/daemon/classes.py
xelis/daemon/events.py
xelis/daemon/http.py
xelis/daemon/methods.py
xelis/daemon/websocket.py
xelis/rpc/__init__.py
xelis/rpc/classes.py
xelis/rpc/http.py
xelis/rpc/util.py
xelis/rpc/websocket.py
xelis/wallet/__init__.py
xelis/wallet/classes.py
xelis/wallet/events.py
xelis/wallet/http.py
xelis/wallet/methods.py
xelis/wallet/websocket.py
xelis/xswd/__init__.py
xelis/xswd/classes.py
xelis/xswd/module.py
xelis_py_sdk-0.4.0.dist-info/METADATA
xelis_py_sdk-0.4.0.dist-info/WHEEL
xelis_py_sdk-0.4.0.dist-info/top_level.txt
xelis_py_sdk-0.4.0.dist-info/RECORD
