Metadata-Version: 2.1
Name: xelis-py-sdk
Version: 0.4.0
Summary: Xelis software development kit for Python
Home-page: https://github.com/xelis-project/xelis-py-sdk
Author: g45t345rt
License: UNKNOWN
Platform: UNKNOWN
Requires-Dist: mashumaro
Requires-Dist: websockets
